Metadata-Version: 1.0
Name: employee001
Version: 0.1
Summary: employee_name
Home-page: UNKNOWN
Author: UNKNOWN
Author-email: UNKNOWN
License: UNKNOWN
Platform: UNKNOWN
